ranking_challenge/__init__.py
ranking_challenge/fake.py
ranking_challenge/fake_test.py
ranking_challenge/grafana_metrics_middleware.py
ranking_challenge/prometheus_metrics_otel_middleware.py
ranking_challenge/request.py
ranking_challenge/response.py
ranking_challenge/survey.py
ranking_challenge/util/__init__.py
ranking_challenge/util/db_utils.py
ranking_challenge-3.4.0.dist-info/LICENSE
ranking_challenge-3.4.0.dist-info/METADATA
ranking_challenge-3.4.0.dist-info/WHEEL
ranking_challenge-3.4.0.dist-info/entry_points.txt
ranking_challenge-3.4.0.dist-info/RECORD
