Metadata-Version: 2.1
Name: ranking_challenge
Version: 3.4.0
Summary: The Prosocial Ranking Challenge
Home-page: https://humancompatible.ai/news/2024/01/18/the-prosocial-ranking-challenge-60000-in-prizes-for-better-social-media-algorithms/
License: MIT
Keywords: ranking,social media,challenge
Author: Ian Baker
Author-email: ian@sonic.net
Requires-Python: >=3.10
Classifier: License :: OSI Approved :: MIT License
Classifier: Programming Language :: Python :: 3
Classifier: Programming Language :: Python :: 3.10
Classifier: Programming Language :: Python :: 3.11
Classifier: Programming Language :: Python :: 3.12
Classifier: Programming Language :: Python :: 3.13
Provides-Extra: module
Requires-Dist: faker ; extra == "module"
Requires-Dist: fastapi
Requires-Dist: prometheus-client
Requires-Dist: pydantic (>=2.6.0) ; extra == "module"
Project-URL: Repository, https://github.com/humancompatibleai/ranking-challenge
Project-URL: blog, https://rankingchallenge.substack.com/
Project-URL: homepage, https://humancompatible.ai/news/2024/01/18/the-prosocial-ranking-challenge-60000-in-prizes-for-better-social-media-algorithms/
Project-URL: repository, https://github.com/humancompatibleai/ranking-challenge
